corona_starken_logistica-1.0.10.dist-info/licenses/LICENSE
starken/connector.py
starken/handler.py
starken/settings.py
corona_starken_logistica-1.0.10.dist-info/METADATA
corona_starken_logistica-1.0.10.dist-info/WHEEL
corona_starken_logistica-1.0.10.dist-info/top_level.txt
corona_starken_logistica-1.0.10.dist-info/RECORD
