Metadata-Version: 2.4
Name: corona-starken-logistica
Version: 1.0.10
Summary: Django Starken Integration
Home-page: https://gitlab.com/linets-projects/python-libraries/django-starken/
Author: Corona Development Team
Author-email: rolguin@corona.cl
License: MIT
Requires-Python: >=3.7
License-File: LICENSE
Requires-Dist: Django>=3
Requires-Dist: requests>=2.25.1
Dynamic: author
Dynamic: author-email
Dynamic: description
Dynamic: description-content-type
Dynamic: home-page
Dynamic: license
Dynamic: license-file
Dynamic: requires-dist
Dynamic: requires-python
Dynamic: summary
